compath_resources/__init__.py
compath_resources/__main__.py
compath_resources/cli.py
compath_resources/constants.py
compath_resources/curation.py
compath_resources/manager.py
compath_resources/parser.py
compath_resources/pathway_size_statistics.py
compath_resources/summarize.py
compath_resources/sync.py
compath_resources/exporters/__init__.py
compath_resources/exporters/bel.py
compath_resources/exporters/rdf.py
compath_resources/resources/__init__.py
compath_resources/resources/decopath.tsv
compath_resources/resources/kegg_reactome.tsv
compath_resources/resources/kegg_wikipathways.tsv
compath_resources/resources/pathbank_kegg.tsv
compath_resources/resources/pathbank_reactome.tsv
compath_resources/resources/pathbank_wikipathways.tsv
compath_resources/resources/reactome_hierarchy.tsv
compath_resources/resources/special_mappings.tsv
compath_resources/resources/wikipathways_reactome.tsv
compath_resources-0.1.1.dist-info/LICENSE
compath_resources-0.1.1.dist-info/METADATA
compath_resources-0.1.1.dist-info/WHEEL
compath_resources-0.1.1.dist-info/entry_points.txt
compath_resources-0.1.1.dist-info/top_level.txt
compath_resources-0.1.1.dist-info/RECORD
