Metadata-Version: 2.1
Name: compath-resources
Version: 0.1.1
Summary: ComPath Resource Utilities
Home-page: https://github.com/compath/compath-resources
Author: Daniel Domingo-Fernández
Author-email: daniel.domingo.fernandez@scai.fraunhofer.de
Maintainer: Daniel Domingo-Fernández
Maintainer-email: daniel.domingo.fernandez@scai.fraunhofer.de
License: MIT
Download-URL: https://github.com/compath/compath-resources/releases
Project-URL: Bug Tracker, https://github.com/compath/compath-resources/issues
Keywords: KEGG,Reactome,WikiPathways,PathBank,Biological Networks,Pathway Analysis,Networks Biology
Platform: UNKNOWN
Classifier: Development Status :: 1 - Planning
Classifier: Intended Audience :: Developers
Classifier: Programming Language :: Python
Classifier: Programming Language :: Python :: 3.7
Classifier: Programming Language :: Python :: 3.8
Classifier: Programming Language :: Python :: 3.9
Classifier: Programming Language :: Python :: 3 :: Only
Classifier: License :: OSI Approved :: MIT License
Requires-Python: >=3.7
Requires-Dist: pybel
Requires-Dist: bio2bel
Requires-Dist: click
Requires-Dist: pandas
Requires-Dist: pystow
Requires-Dist: xlrd
Requires-Dist: seaborn
Requires-Dist: matplotlib
Requires-Dist: more-click
Requires-Dist: bioregistry
Requires-Dist: openpyxl
Provides-Extra: docs
Requires-Dist: sphinx ; extra == 'docs'
Requires-Dist: sphinx-rtd-theme ; extra == 'docs'
Requires-Dist: sphinx-click ; extra == 'docs'
Requires-Dist: sphinx-autodoc-typehints ; extra == 'docs'
Provides-Extra: rdf
Requires-Dist: rdflib ; extra == 'rdf'
